byteblower/test_cases/tr_398/.gitignore
byteblower/test_cases/tr_398/__init__.py
byteblower/test_cases/tr_398/__main__.py
byteblower/test_cases/tr_398/_endpoint_factory.py
byteblower/test_cases/tr_398/_port_factory.py
byteblower/test_cases/tr_398/_version.py
byteblower/test_cases/tr_398/airtime_fairness.py
byteblower/test_cases/tr_398/cli.py
byteblower/test_cases/tr_398/definitions.py
byteblower/test_cases/tr_398/exceptions.py
byteblower/test_cases/tr_398/report_generator.py
byteblower/test_cases/tr_398/templates/report.html
byteblower/test_cases/tr_398/templates/report_footer.html
byteblower/test_cases/tr_398/templates/report_head_style.html
byteblower/test_cases/tr_398/templates/report_header.html
byteblower/test_cases/tr_398/templates/report_main.html
byteblower/test_cases/tr_398/templates/report_pass_fail.html
byteblower/test_cases/tr_398/templates/results_summary.html
byteblower/test_cases/tr_398/templates/css/embedded-fonts.css
byteblower/test_cases/tr_398/templates/css/testframework.css
byteblower/test_cases/tr_398/templates/css/tr398.css
byteblower_test_cases_tr_398-1.0.0.post1.dist-info/entry_points.txt
byteblower_test_cases_tr_398-1.0.0.post1.dist-info/LICENSE
byteblower_test_cases_tr_398-1.0.0.post1.dist-info/WHEEL
byteblower_test_cases_tr_398-1.0.0.post1.dist-info/METADATA
byteblower_test_cases_tr_398-1.0.0.post1.dist-info/RECORD
